{ "X3D": {
    "encoding":"UTF-8",
    "@profile":"Immersive",
    "@version":"3.3",
    "@xsd:noNamespaceSchemaLocation":"http://www.web3d.org/specifications/x3d-3.3.xsd",
    "JSON schema":"http://www.web3d.org/specifications/x3d-3.3-JSONSchema.json",
    "head": {
        "component": [
          {
            "@name":"Geometry2D",
            "@level":2
          }
        ],
        "meta": [
          {
            "@name":"title",
            "@content":"Polypoint2D.x3d"
          },
          {
            "@name":"description",
            "@content":"Example of Polypoint2D showing a simple set of points."
          },
          {
            "@name":"creator",
            "@content":"Leonard Daly and Don Brutzman"
          },
          {
            "@name":"created",
            "@content":"17 April 2006"
          },
          {
            "@name":"modified",
            "@content":"24 May 2008"
          },
          {
            "@name":"reference",
            "@content":"http://X3dGraphics.com"
          },
          {
            "@name":"reference",
            "@content":"http://www.web3d.org/x3d/content/examples/X3dResources.html"
          },
          {
            "@name":"rights",
            "@content":"Copyright 2006, Daly Realism and Don Brutzman"
          },
          {
            "@name":"subject",
            "@content":"X3D book, X3D graphics, X3D-Edit, http://www.x3dGraphics.com"
          },
          {
            "@name":"identifier",
            "@content":"http://X3dGraphics.com/examples/X3dForWebAuthors/Chapter10-Geometry2D/Polypoint2D.x3d"
          },
          {
            "@name":"generator",
            "@content":"X3D-Edit 3.3, https://savage.nps.edu/X3D-Edit"
          },
          {
            "@name":"license",
            "@content":"../license.html"
          },
          {
            "@name":"translated",
            "@content":"19 March 2017"
          },
          {
            "@name":"generator",
            "@content":"X3dToJson.xslt, http://www.web3d.org/x3d/stylesheets/X3dToJson.html"
          },
          {
            "@name":"warning",
            "@content":"An experimental version of X3D JSON encoding is used for this scene.  Status online at http://www.web3d.org/wiki/index.php/X3D_JSON_Encoding"
          }
        ]
    },
    "Scene": {
        "-children":[
          { "Viewpoint":
            {
              "@description":"Polypoint2D example",
              "@orientation":[0,1,0,0.159],
              "@position":[1.21,-0.22,8.04]
            }
          },
          { "Group":
            {
              "-children":[
                { "Shape":
                  {
                    "-geometry":
                      { "Polypoint2D":
                        {
                          "@point":[-3,2,-3,0,-1,0,-3,-1,-2,-2,0,-2,0,-1,-2,-1,3,-1.5,3,1.5,2,-1,0.5,3,-0.5,1.5,1.5,1.5]
                        }
                      },
                    "-appearance":
                      { "Appearance":
                        {
                          "@DEF":"MagentaAppearance",
                          "-material":
                            { "Material":
                              {
                                "@diffuseColor":[1,0,0],
                                "@emissiveColor":[0,0,1],
                                "@specularColor":[0,0.8,0]
                              }
                            }
                        }
                      }
                  }
                }
              ]
            }
          }
        ]
    }
  }
}